.DS_Store
image_process_dio/.DS_Store
image_process_dio/__init__.py
image_process_dio/process/__init__.py
image_process_dio/process/combination.py
image_process_dio/process/transformation.py
image_process_dio/utils/__init__.py
image_process_dio/utils/io.py
image_process_dio/utils/plot.py
image_process_DIO-0.0.3.dist-info/METADATA
image_process_DIO-0.0.3.dist-info/WHEEL
image_process_DIO-0.0.3.dist-info/top_level.txt
image_process_DIO-0.0.3.dist-info/RECORD
