Metadata-Version: 2.1
Name: image-process-DIO
Version: 0.0.3
Summary: Test package for image processing
Home-page: https://github.com/glauciodrumond/unimed-datascience/IMAGE_PROCESS_PKG
Author: glauciodrumond
Author-email: glauciotad@gmail.com
Requires-Python: >=3.7
Requires-Dist: matplotlib
Requires-Dist: numpy
Requires-Dist: scikit-image (>=0.16.1)
